tcoreapi_mq/__init__.py
tcoreapi_mq/tcoreapi_mq.py
tcoreapi_mq/sample/__init__.py
tcoreapi_mq/sample/main_sample完整demo.py
tcoreapi_mq/sample/历史数据回补并动态获取最新K是否产生.py
tcoreapi_mq/sample/实时行情订阅demo.py
tcoreapi_mq-4.0.22.dist-info/LICENSE
tcoreapi_mq-4.0.22.dist-info/METADATA
tcoreapi_mq-4.0.22.dist-info/WHEEL
tcoreapi_mq-4.0.22.dist-info/top_level.txt
tcoreapi_mq-4.0.22.dist-info/RECORD
