Metadata-Version: 2.1
Name: tcoreapi-mq
Version: 4.0.22
Summary: tcoreapi_mq
Home-page: https://voltrader.icetech.com.cn/
Author: ICE Technology
Author-email: mcsupport@icetech.com.cn
License: UNKNOWN
Platform: UNKNOWN
Classifier: Programming Language :: Python :: 3
Classifier: Operating System :: OS Independent
Requires-Dist: pyzmq
